adguard_sync/__init__.py
adguard_sync/sync.py
adguard_sync-1.0.dist-info/METADATA
adguard_sync-1.0.dist-info/WHEEL
adguard_sync-1.0.dist-info/top_level.txt
adguard_sync-1.0.dist-info/RECORD
