Metadata-Version: 2.1
Name: adguard-sync
Version: 1.0
Summary: Sync dns rewrites on multiple adguards
Home-page: https://github.com/mkapra/adguard-sync
Author: Maximilian Kapra
Author-email: maximilian@kapra.de
License: UNKNOWN
Project-URL: Bug Tracker, https://github.com/mkapra/adguard-sync/issues
Platform: UNKNOWN
Classifier: Programming Language :: Python :: 3
Classifier: License :: OSI Approved :: MIT License
Classifier: Operating System :: OS Independent
Requires-Python: >=3.9
